spaceone/__init__.py
spaceone/billing/__init__.py
spaceone/billing/api/__init__.py
spaceone/billing/api/v1/__init__.py
spaceone/billing/api/v1/billing.py
spaceone/billing/api/v1/data_source.py
spaceone/billing/conf/__init__.py
spaceone/billing/conf/global_conf.py
spaceone/billing/conf/proto_conf.py
spaceone/billing/connector/__init__.py
spaceone/billing/connector/billing_plugin_connector.py
spaceone/billing/connector/identity_connector.py
spaceone/billing/connector/inventory_connector.py
spaceone/billing/connector/plugin_connector.py
spaceone/billing/connector/repository_connector.py
spaceone/billing/connector/secret_connector.py
spaceone/billing/error/__init__.py
spaceone/billing/error/billing.py
spaceone/billing/error/data_source.py
spaceone/billing/info/__init__.py
spaceone/billing/info/billing_info.py
spaceone/billing/info/common_info.py
spaceone/billing/info/data_source_info.py
spaceone/billing/lib/__init__.py
spaceone/billing/manager/__init__.py
spaceone/billing/manager/data_source_manager.py
spaceone/billing/manager/identity_manager.py
spaceone/billing/manager/plugin_manager.py
spaceone/billing/manager/repository_manager.py
spaceone/billing/manager/secret_manager.py
spaceone/billing/model/__init__.py
spaceone/billing/model/data_source_model.py
spaceone/billing/service/__init__.py
spaceone/billing/service/billing_service.py
spaceone/billing/service/data_source_service.py
spaceone_billing-1.10.0.dist-info/METADATA
spaceone_billing-1.10.0.dist-info/WHEEL
spaceone_billing-1.10.0.dist-info/top_level.txt
spaceone_billing-1.10.0.dist-info/RECORD
