Metadata-Version: 2.1
Name: spaceone-billing
Version: 1.10.0
Summary: SpaceONE billing service
Home-page: https://www.spaceone.dev/
Author: MEGAZONE SpaceONE Team
Author-email: admin@spaceone.dev
License: Apache License 2.0
Platform: UNKNOWN
Requires-Dist: spaceone-core
Requires-Dist: spaceone-api
Requires-Dist: mongoengine
Requires-Dist: redis
Requires-Dist: schematics
Requires-Dist: pandas
